LICENSE
MANIFEST.in
README.md
pyproject.toml
setup.py
slidepy/__init__.py
slidepy/_ext.pyx
slidepy/slide.py
slidepy.egg-info/PKG-INFO
slidepy.egg-info/SOURCES.txt
slidepy.egg-info/dependency_links.txt
slidepy.egg-info/requires.txt
slidepy.egg-info/top_level.txt
slidepy/augment/augment.c
slidepy/augment/augment.h
slidepy/com/com.c
slidepy/com/com.h
slidepy/mp_math/mp_math.c
slidepy/mp_math/mp_math.h