Metadata-Version: 2.1
Name: slidepy
Version: 0.0.1
Summary: Fast multi-threaded 3D landslide modelling with SIMD support
Home-page: https://github.com/asenogles/slidepy
Author: asenogles
License: LGPL v3
Platform: UNKNOWN
Requires-Python: >=3.6
License-File: LICENSE
